{
    "scene_id": "ffgfhjhjjhjkkjkllklkjhhg",
    "scene_name": "--bhgfdfdf",
    "timestamp_range": {
        "start": "2018-07-23T20:28:47.647951",
        "end": "2018-07-23T20:35:00.000000"
    },
    "average_position": [411.3039349319818, 1180.8903791765097, 0.0],
    "number_of_frames_combined": 15,
    "condensed_frames": [
        {
            "frame_id": "condensed_frame_001",
            "average_timestamp": "2018-07-23T20:30:00.000000",
            "average_position": [400.0, 1170.0, 0.0],
            "annotations": [
                {
                    "category": "movable_object.barrier",
                    "average_location": [399.773, 1169.799, 0.536],
                    "size": [1.99, 0.651, 1.107],
                    "rotation": [-0.9837693673542263, 0.0, 0.0, 0.1794375430490104],
                    "velocity": [0.0, 0.0, 0.1],
                    "num_lidar_pts": 27,
                    "num_radar_pts": 2
                },
                {
                    "category": "vehicle.car",
                    "average_location": [360.095, 1122.376, 0.7],
                    "size": [1.875, 4.363, 1.441],
                    "rotation": [0.9820575882257031, 0.0, 0.0, -0.1885812647330467],
                    "velocity": [-0.06179561, 0.02544525, 0.1326788],
                    "num_lidar_pts": 0,
                    "num_radar_pts": 0
                }
            ],
            "frame_count-- no of condensed frames": 5
        },
        {
            "frame_id": "condensed_frame_002",
            "average_timestamp": "2018-07-23T20:32:00.000000",
            "average_position": [420.0, 1190.0, 0.0],
            "annotations": [
                {
                    "category": "pedestrian",
                    "average_location": [410.5, 1185.0, 0.0],
                    "size": [0.6, 0.6, 1.8],
                    "rotation": [0.0, 0.0, 0.0, 1.0],
                    "velocity": [0.2, 0.1, 0.0],
                    "num_lidar_pts": 10,
                    "num_radar_pts": 0
                }
            ],
            "frame_count": 3
        }
    ]
}


